{
  "skipgram_top": [
    {
      "phase": "base",
      "architecture": "skipgram",
      "dim": "200",
      "window": "7",
      "negative": "5",
      "start_lr": "0.005",
      "epochs": "20",
      "subsample_t": "0.001",
      "vocab_size": "819",
      "train_time_s": "13.59",
      "loss_start": "0.693147",
      "loss_end": "0.693133",
      "loss_drop": "1.4e-05",
      "semantic_score": "0.3917",
      "nn_score": "0.3333",
      "analogy_score": "0.5",
      "sat_ratio": "0.0",
      "mean_top1_sim": "0.5598",
      "top1_sim_std": "0.1677",
      "saturation_penalty": "0.0",
      "model_tag": "skipgram_d200_w7_n5_lr0p005_ep20_ss1em03"
    },
    {
      "phase": "base",
      "architecture": "skipgram",
      "dim": "200",
      "window": "3",
      "negative": "10",
      "start_lr": "0.005",
      "epochs": "20",
      "subsample_t": "0.001",
      "vocab_size": "819",
      "train_time_s": "7.37",
      "loss_start": "0.693147",
      "loss_end": "0.693129",
      "loss_drop": "1.8e-05",
      "semantic_score": "0.3483",
      "nn_score": "0.2667",
      "analogy_score": "0.5",
      "sat_ratio": "0.0",
      "mean_top1_sim": "0.5558",
      "top1_sim_std": "0.1732",
      "saturation_penalty": "0.0",
      "model_tag": "skipgram_d200_w3_n10_lr0p005_ep20_ss1em03"
    },
    {
      "phase": "tuned",
      "architecture": "skipgram",
      "dim": "200",
      "window": "7",
      "negative": "5",
      "start_lr": "0.002",
      "epochs": "40",
      "subsample_t": "0.001",
      "vocab_size": "819",
      "train_time_s": "27.43",
      "loss_start": "0.693147",
      "loss_end": "0.693141",
      "loss_drop": "6e-06",
      "semantic_score": "0.3483",
      "nn_score": "0.2667",
      "analogy_score": "0.5",
      "sat_ratio": "0.0",
      "mean_top1_sim": "0.3833",
      "top1_sim_std": "0.115",
      "saturation_penalty": "0.0",
      "model_tag": "skipgram_d200_w7_n5_lr0p002_ep40_ss1em03"
    },
    {
      "phase": "tuned",
      "architecture": "skipgram",
      "dim": "200",
      "window": "7",
      "negative": "5",
      "start_lr": "0.005",
      "epochs": "20",
      "subsample_t": "0.0005",
      "vocab_size": "819",
      "train_time_s": "10.11",
      "loss_start": "0.693147",
      "loss_end": "0.693143",
      "loss_drop": "4e-06",
      "semantic_score": "0.3483",
      "nn_score": "0.2667",
      "analogy_score": "0.5",
      "sat_ratio": "0.0",
      "mean_top1_sim": "0.3381",
      "top1_sim_std": "0.0812",
      "saturation_penalty": "0.0",
      "model_tag": "skipgram_d200_w7_n5_lr0p005_ep20_ss5em04"
    },
    {
      "phase": "tuned",
      "architecture": "skipgram",
      "dim": "200",
      "window": "3",
      "negative": "10",
      "start_lr": "0.002",
      "epochs": "40",
      "subsample_t": "0.001",
      "vocab_size": "819",
      "train_time_s": "14.74",
      "loss_start": "0.693147",
      "loss_end": "0.69314",
      "loss_drop": "8e-06",
      "semantic_score": "0.3339",
      "nn_score": "0.2444",
      "analogy_score": "0.5",
      "sat_ratio": "0.0",
      "mean_top1_sim": "0.3913",
      "top1_sim_std": "0.1173",
      "saturation_penalty": "0.0",
      "model_tag": "skipgram_d200_w3_n10_lr0p002_ep40_ss1em03"
    },
    {
      "phase": "tuned",
      "architecture": "skipgram",
      "dim": "200",
      "window": "3",
      "negative": "10",
      "start_lr": "0.005",
      "epochs": "20",
      "subsample_t": "0.0005",
      "vocab_size": "819",
      "train_time_s": "5.56",
      "loss_start": "0.693147",
      "loss_end": "0.693142",
      "loss_drop": "5e-06",
      "semantic_score": "0.3339",
      "nn_score": "0.2444",
      "analogy_score": "0.5",
      "sat_ratio": "0.0",
      "mean_top1_sim": "0.3514",
      "top1_sim_std": "0.0905",
      "saturation_penalty": "0.0",
      "model_tag": "skipgram_d200_w3_n10_lr0p005_ep20_ss5em04"
    },
    {
      "phase": "tuned",
      "architecture": "skipgram",
      "dim": "200",
      "window": "3",
      "negative": "10",
      "start_lr": "0.002",
      "epochs": "40",
      "subsample_t": "0.0005",
      "vocab_size": "819",
      "train_time_s": "11.09",
      "loss_start": "0.693147",
      "loss_end": "0.693145",
      "loss_drop": "2e-06",
      "semantic_score": "0.2761",
      "nn_score": "0.1556",
      "analogy_score": "0.5",
      "sat_ratio": "0.0",
      "mean_top1_sim": "0.2558",
      "top1_sim_std": "0.0456",
      "saturation_penalty": "0.0",
      "model_tag": "skipgram_d200_w3_n10_lr0p002_ep40_ss5em04"
    },
    {
      "phase": "base",
      "architecture": "skipgram",
      "dim": "100",
      "window": "3",
      "negative": "10",
      "start_lr": "0.005",
      "epochs": "20",
      "subsample_t": "0.001",
      "vocab_size": "819",
      "train_time_s": "7.32",
      "loss_start": "0.693147",
      "loss_end": "0.69311",
      "loss_drop": "3.7e-05",
      "semantic_score": "0.2311",
      "nn_score": "0.3556",
      "analogy_score": "0.0",
      "sat_ratio": "0.0",
      "mean_top1_sim": "0.5312",
      "top1_sim_std": "0.1298",
      "saturation_penalty": "0.0",
      "model_tag": "skipgram_d100_w3_n10_lr0p005_ep20_ss1em03"
    }
  ],
  "cbow_top": [
    {
      "phase": "base",
      "architecture": "cbow",
      "dim": "100",
      "window": "3",
      "negative": "5",
      "start_lr": "0.01",
      "epochs": "20",
      "subsample_t": "0.001",
      "vocab_size": "819",
      "train_time_s": "1.67",
      "loss_start": "0.693147",
      "loss_end": "0.693146",
      "loss_drop": "1e-06",
      "semantic_score": "0.0",
      "nn_score": "0.0",
      "analogy_score": "0.0",
      "sat_ratio": "0.0",
      "mean_top1_sim": "0.318",
      "top1_sim_std": "0.0366",
      "saturation_penalty": "0.0",
      "model_tag": "cbow_d100_w3_n5_lr0p01_ep20_ss1em03"
    },
    {
      "phase": "base",
      "architecture": "cbow",
      "dim": "100",
      "window": "3",
      "negative": "10",
      "start_lr": "0.01",
      "epochs": "20",
      "subsample_t": "0.001",
      "vocab_size": "819",
      "train_time_s": "1.68",
      "loss_start": "0.693147",
      "loss_end": "0.693146",
      "loss_drop": "1e-06",
      "semantic_score": "0.0",
      "nn_score": "0.0",
      "analogy_score": "0.0",
      "sat_ratio": "0.0",
      "mean_top1_sim": "0.3182",
      "top1_sim_std": "0.0367",
      "saturation_penalty": "0.0",
      "model_tag": "cbow_d100_w3_n10_lr0p01_ep20_ss1em03"
    },
    {
      "phase": "base",
      "architecture": "cbow",
      "dim": "100",
      "window": "3",
      "negative": "15",
      "start_lr": "0.01",
      "epochs": "20",
      "subsample_t": "0.001",
      "vocab_size": "819",
      "train_time_s": "1.71",
      "loss_start": "0.693147",
      "loss_end": "0.693144",
      "loss_drop": "3e-06",
      "semantic_score": "0.0",
      "nn_score": "0.0",
      "analogy_score": "0.0",
      "sat_ratio": "0.0",
      "mean_top1_sim": "0.3179",
      "top1_sim_std": "0.0369",
      "saturation_penalty": "0.0",
      "model_tag": "cbow_d100_w3_n15_lr0p01_ep20_ss1em03"
    }
  ]
}